<?xml version="1.0" encoding="utf-8"?>
<Package
  xmlns="http://schemas.microsoft.com/appx/manifest/foundation/windows10"
  xmlns:uap="http://schemas.microsoft.com/appx/manifest/uap/windows10"
  xmlns:rescap="http://schemas.microsoft.com/appx/manifest/foundation/windows10/restrictedcapabilities"
  xmlns:desktop="http://schemas.microsoft.com/appx/manifest/desktop/windows10"
  IgnorableNamespaces="uap rescap desktop">

  <!-- Publisher CN must match your Partner Center identity exactly.
       After registering at https://partner.microsoft.com/dashboard,
       replace the placeholder below with the CN= string from your
       certificate info page. -->
  <Identity
    Name="BATorrent.BATorrent"
    Version="3.0.2.0"
    Publisher="CN=D838099A-EE48-4F66-92B6-2A44F20C37EF"
    ProcessorArchitecture="x64" />

  <Properties>
    <DisplayName>BATorrent</DisplayName>
    <PublisherDisplayName>BATorrent</PublisherDisplayName>
    <Logo>assets\StoreLogo.png</Logo>
    <Description>A modern, open-source BitTorrent client focused on privacy, performance, and clarity. No ads, no telemetry.</Description>
  </Properties>

  <Dependencies>
    <TargetDeviceFamily Name="Windows.Desktop" MinVersion="10.0.19041.0" MaxVersionTested="10.0.22621.0" />
  </Dependencies>

  <Resources>
    <Resource Language="en-us" />
    <Resource Language="pt-br" />
    <Resource Language="zh-hans" />
    <Resource Language="ja" />
    <Resource Language="ru" />
    <Resource Language="es" />
    <Resource Language="de" />
  </Resources>

  <Applications>
    <Application Id="BATorrent" Executable="BATorrent.exe" EntryPoint="Windows.FullTrustApplication">
      <uap:VisualElements
        DisplayName="BATorrent"
        Description="Open-source BitTorrent client with VPN kill switch, anti-Xunlei blocking, Tor proxy, Telegram notifications, Discord activity, and 7 languages."
        BackgroundColor="#0e0a0a"
        Square150x150Logo="assets\Square150x150Logo.png"
        Square44x44Logo="assets\Square44x44Logo.png">
        <uap:DefaultTile Wide310x150Logo="assets\Wide310x150Logo.png" Square71x71Logo="assets\Square71x71Logo.png" />
      </uap:VisualElements>

      <Extensions>
        <uap:Extension Category="windows.fileTypeAssociation">
          <uap:FileTypeAssociation Name="torrent">
            <uap:SupportedFileTypes>
              <uap:FileType>.torrent</uap:FileType>
            </uap:SupportedFileTypes>
            <uap:DisplayName>Torrent File</uap:DisplayName>
          </uap:FileTypeAssociation>
        </uap:Extension>

        <uap:Extension Category="windows.protocol">
          <uap:Protocol Name="magnet">
            <uap:DisplayName>Magnet Link</uap:DisplayName>
          </uap:Protocol>
        </uap:Extension>
      </Extensions>
    </Application>
  </Applications>

  <!-- Full-trust Win32 app — no AppContainer sandbox. Unrestricted
       network + file system access via Desktop Bridge. -->
  <Capabilities>
    <rescap:Capability Name="runFullTrust" />
  </Capabilities>
</Package>
